<?xml version="1.0" encoding="UTF-8"?>
<resources>
  <string name="Vault_AllFiles_Title"></string>
  <string name="Vault_Images_Title"></string>
  <string name="Vault_Files_Title"></string>
  <string name="Vault_Documents_Title"></string>
  <string name="Vault_Audios_Title"></string>
  <string name="Vault_Videos_Title">വീഡിയോകള്‍</string>
  <string name="Vault_Others_Title"></string>
  <string name="Vault_Select_Title"></string>
  <string name="Vault_RecentFiles">Recent files</string>
  <string name="Vault_PhotosAndVideos_Title"></string>
  <string name="Vault_FavoriteForms_Title">Favorite forms</string>
  <string name="Vault_Empty_Msg"></string>
  <string name="Vault_Move_SheetDesc"></string>
  <string name="Vault_Rename_SheetAction"></string>
  <string name="Vault_Save_SheetAction">സംരക്ഷിക്കുക</string>
  <string name="Vault_Delete_SheetAction">നീക്കം ചെയ്യുക</string>
  <string name="Vault_Share_SheetAction">പങ്കുവയ്ക്കുക</string>
  <string name="Vault_Upload_SheetAction">അപ്‌ലോഡ്</string>
  <string name="Vault_File_SheetAction"></string>
  <string name="Vault_FileInfo"></string>
  <string name="Vault_FileSize"></string>
  <string name="Vault_FileFormat"></string>
  <string name="Vault_FileCreated"></string>
  <string name="Vault_FileResolution"></string>
  <string name="Vault_FileLength"></string>
  <string name="Vault_FilePath"></string>
  <string name="Vault_RenameFile_SheetTitle"></string>
  <plurals name="Vault_DeleteFile_SheetTitle">
    <item quantity="one"></item>
    <item quantity="other"></item>
  </plurals>
  <plurals name="Vault_deleteFile_SheetDesc">
    <item quantity="one"></item>
    <item quantity="other"></item>
  </plurals>
  <string name="Vault_SortNameAsc_SheetAction"></string>
  <string name="Vault_SortNameDesc_SheetAction"></string>
  <string name="Vault_SortDateAsc_SheetAction">പുതിയത് മുതൽ പഴയതിലേക്ക്</string>
  <string name="Vault_SortDateDesc_SheetAction">പഴയത് മുതൽ പുതിയതിലേക്ക്</string>
  <string name="Vault_ManageFiles_SheetTitle"></string>
  <string name="Vault_DeleteFile_SheetDesc"></string>
  <string name="Vault_TakePhotoVideo_SheetAction"></string>
  <string name="Vault_RecordAudio_SheetAction"></string>
  <string name="Vault_Import_SheetAction"></string>
  <string name="Vault_ImportDelete_SheetAction"></string>
  <string name="Vault_CreateFolder_SheetTitle"></string>
  <string name="Vault_MoveHere"></string>
  <string name="Vault_ViewerOther_SheetDesc"></string>
  <string name="Vault_Export_SheetAction">ഉപകരണത്തിലേക്ക് സൂക്ഷിക്കുക</string>
  <plurals name="Vault_Items">
    <item quantity="one"></item>
    <item quantity="other"></item>
  </plurals>
  <string name="Vault_No_Files_Title"></string>
  <string name="Vault_FavoriteTemplates_Title"></string>
</resources>
